Workbook

Sheet Sales
A1: Regional Sales 2026
A2: Monthly revenue by region (USD). Totals and growth are formulas.
A3: Region | B3: Jan | C3: Feb | D3: Mar | E3: Apr | F3: May | G3: Jun | H3: Jul | I3: Aug | J3: Sep | K3: Oct | L3: Nov | M3: Dec | N3: Total | O3: Growth
A4: North | B4: 42100 | C4: 39800 | D4: 45250 | E4: 47100 | F4: 51230 | G4: 53900 | H4: 50110 | I4: 52480 | J4: 55120 | K4: 57900 | L4: 61200 | M4: 68450 | N4: =SUM(B4:M4) -> 624640 | O4: =IF(B4=0,0,M4/B4-1) -> 0.62589074
A5: South | B5: 31200 | C5: 30150 | D5: 33900 | E5: 35020 | F5: 36880 | G5: 38110 | H5: 37450 | I5: 39200 | J5: 40310 | K5: 42780 | L5: 44900 | M5: 49800 | N5: =SUM(B5:M5) -> 459700 | O5: =IF(B5=0,0,M5/B5-1) -> 0.59615385
A6: East | B6: 27800 | C6: 28900 | D6: 29450 | E6: 31200 | F6: 30980 | G6: 33450 | H6: 34120 | I6: 35800 | J6: 36020 | K6: 37950 | L6: 39400 | M6: 43150 | N6: =SUM(B6:M6) -> 408220 | O6: =IF(B6=0,0,M6/B6-1) -> 0.55215827
A7: West | B7: 36500 | C7: 35100 | D7: 38750 | E7: 40200 | F7: 42150 | G7: 41980 | H7: 43300 | I7: 45120 | J7: 47800 | K7: 49010 | L7: 50500 | M7: 56300 | N7: =SUM(B7:M7) -> 526710 | O7: =IF(B7=0,0,M7/B7-1) -> 0.54246575
A8: Central | B8: 18900 | C8: 19450 | D8: 20100 | E8: 21850 | F8: 22400 | G8: 23900 | H8: 24150 | I8: 25020 | J8: 26300 | K8: 27100 | L8: 28850 | M8: 31900 | N8: =SUM(B8:M8) -> 289920 | O8: =IF(B8=0,0,M8/B8-1) -> 0.68783069
A9: Total | B9: =SUM(B4:B8) -> 156500 | C9: =SUM(C4:C8) -> 153400 | D9: =SUM(D4:D8) -> 167450 | E9: =SUM(E4:E8) -> 175370 | F9: =SUM(F4:F8) -> 183640 | G9: =SUM(G4:G8) -> 191340 | H9: =SUM(H4:H8) -> 189130 | I9: =SUM(I4:I8) -> 197620 | ... N9: =SUM(N4:N8) -> 2309190
A11: Best month | B11: =INDEX(B3:M3,MATCH(MAX(B9:M9),B9:M9,0)) -> Dec
A12: Average month | B12: =AVERAGE(B9:M9) -> 192432.5
A13: Report date | B13: =DATE(2026,12,31) -> 46387

Sheet Budget
A1: Operating Budget FY2026
A3: Category | B3: Owner | C3: Budget | D3: Actual | E3: Variance | F3: Status
A4: Salaries | B4: People | C4: 840000 | D4: 826500 | E4: =C4-D4 -> 13500 | F4: =IF(D4>C4,"Over","On track") -> On track
A5: Marketing | B5: Growth | C5: 145000 | D5: 162300 | E5: =C5-D5 -> -17300 | F5: =IF(D5>C5,"Over","On track") -> Over
A6: Cloud hosting | B6: Engineering | C6: 96000 | D6: 88750 | E6: =C6-D6 -> 7250 | F6: =IF(D6>C6,"Over","On track") -> On track
A7: Office and facilities | B7: Operations | C7: 72000 | D7: 74100 | E7: =C7-D7 -> -2100 | F7: =IF(D7>C7,"Over","On track") -> Over
A8: Travel | B8: Sales | C8: 38000 | D8: 29400 | E8: =C8-D8 -> 8600 | F8: =IF(D8>C8,"Over","On track") -> On track
A9: Training | B9: People | C9: 24000 | D9: 19850 | E9: =C9-D9 -> 4150 | F9: =IF(D9>C9,"Over","On track") -> On track
A10: Software licences | B10: Engineering | C10: 51000 | D10: 53600 | E10: =C10-D10 -> -2600 | F10: =IF(D10>C10,"Over","On track") -> Over
A11: Contingency | B11: Finance | C11: 30000 | D11: 0 | E11: =C11-D11 -> 30000 | F11: =IF(D11>C11,"Over","On track") -> On track
A12: Total | C12: =SUM(C4:C11) -> 1296000 | D12: =SUM(D4:D11) -> 1254500 | E12: =SUM(E4:E11) -> 41500
A13: Spent | D13: =D12/C12 -> 0.9679784

Sheet Summary
A1: Summary
A3: Metric | B3: Value | C3: Target | D3: Met
A4: Annual revenue | B4: =Sales!N9 -> 2309190 | C4: 2400000 | D4: =IF(B4>=C4,"Yes","No") -> No
A5: Operating cost | B5: =Budget!D12 -> 1254500 | C5: 1300000 | D5: =IF(B5>=C5,"Yes","No") -> No
A6: Operating margin | B6: =(B4-B5)/B4 -> 0.45673591 | C6: 0.4 | D6: =IF(B6>=C6,"Yes","No") -> Yes
A7: Budget spent | B7: =Budget!D13 -> 0.9679784 | C7: 0.95 | D7: =IF(B7>=C7,"Yes","No") -> Yes
A8: Regions over 500k | B8: =COUNTIF(Sales!N4:N8,">500000") -> 2 | C8: 3 | D8: =IF(B8>=C8,"Yes","No") -> No
A11: Month | B11: All regions
A12: Jan | B12: =Sales!B9 -> 156500
A13: Feb | B13: =Sales!C9 -> 153400
A14: Mar | B14: =Sales!D9 -> 167450
A15: Apr | B15: =Sales!E9 -> 175370
A16: May | B16: =Sales!F9 -> 183640
A17: Jun | B17: =Sales!G9 -> 191340
A18: Jul | B18: =Sales!H9 -> 189130
A19: Aug | B19: =Sales!I9 -> 197620
A20: Sep | B20: =Sales!J9 -> 205550
A21: Oct | B21: =Sales!K9 -> 214740
A22: Nov | B22: =Sales!L9 -> 224850
A23: Dec | B23: =Sales!M9 -> 249600
